ansible/module_utils/dotdiff.py
ansible_dotdiff-0.1.5.dist-info/METADATA
ansible_dotdiff-0.1.5.dist-info/RECORD
ansible_dotdiff-0.1.5.dist-info/WHEEL
ansible_dotdiff-0.1.5.dist-info/top_level.txt
