Metadata-Version: 2.1
Name: ansible-dotdiff
Version: 0.1.5
Summary: Nested structure diff library with dot-path notation for Ansible
Home-page: https://github.com/Klarrio/ansible-dotdiff
Author: Timo Beckers
Author-email: timo.beckers@klarrio.com
License: UNKNOWN
Platform: UNKNOWN
Requires-Dist: ansible (>=2.1.0)
